nisystemlink_examples/__init__.py
nisystemlink_examples/testdata/__init__.py
nisystemlink_examples/testdata/simulator.py
nisystemlink_examples-0.1.1.dist-info/METADATA
nisystemlink_examples-0.1.1.dist-info/WHEEL
nisystemlink_examples-0.1.1.dist-info/licenses/LICENSE
nisystemlink_examples-0.1.1.dist-info/RECORD
