Metadata-Version: 2.4
Name: nisystemlink-examples
Version: 0.1.1
Summary: NI SystemLink examples and demo utilities
License: MIT
License-File: LICENSE
Keywords: nisystemlink,systemlink
Author: National Instruments
Maintainer: Adam Arnesen
Maintainer-email: adam.arnesen@emerson.com
Requires-Python: >=3.10,<4.0
Classifier: License :: OSI Approved :: MIT License
Classifier: Programming Language :: Python :: 3
Classifier: Programming Language :: Python :: 3.10
Classifier: Programming Language :: Python :: 3.11
Classifier: Programming Language :: Python :: 3.12
Classifier: Programming Language :: Python :: 3.13
Classifier: Programming Language :: Python :: 3.14
Requires-Dist: nisystemlink-clients (>=2.18.0,<3.0.0)
Requires-Dist: requests (>=2.32.5,<3.0.0)
Requires-Dist: urllib3 (>=2.6.0,<3.0.0)
